setup.py
handle_distributions/Binomialdistribution.py
handle_distributions/Gaussiandistribution.py
handle_distributions/Generaldistribution.py
handle_distributions/__init__.py
handle_distributions.egg-info/PKG-INFO
handle_distributions.egg-info/SOURCES.txt
handle_distributions.egg-info/dependency_links.txt
handle_distributions.egg-info/not-zip-safe
handle_distributions.egg-info/top_level.txt