Metadata-Version: 2.1
Name: handle-distributions
Version: 0.2
Summary: Gaussian and binomial distributions
Home-page: UNKNOWN
Author: Chamod perera
Author-email: chamodperera87@gmail.com
License: UNKNOWN
Platform: UNKNOWN
